azureml/__init__.py
azureml/contrib/__init__.py
azureml/contrib/interpret/__init__.py
azureml/contrib/interpret/explanation/__init__.py
azureml/contrib/interpret/explanation/explanation_client/__init__.py
azureml_contrib_interpret-1.23.0.dist-info/DESCRIPTION.rst
azureml_contrib_interpret-1.23.0.dist-info/LICENSE.txt
azureml_contrib_interpret-1.23.0.dist-info/METADATA
azureml_contrib_interpret-1.23.0.dist-info/RECORD
azureml_contrib_interpret-1.23.0.dist-info/WHEEL
azureml_contrib_interpret-1.23.0.dist-info/metadata.json
azureml_contrib_interpret-1.23.0.dist-info/top_level.txt
