Metadata-Version: 2.0
Name: azureml-contrib-interpret
Version: 1.23.0
Summary: ML contrib interpret package contains experimental functionality to interpret ML models
Home-page: https://docs.microsoft.com/python/api/overview/azure/ml/?view=azure-ml-py
Author: Microsoft Corp
License: Proprietary https://aka.ms/azureml-preview-sdk-license 
Platform: UNKNOWN
Requires-Python: >=3.5,<4
Provides-Extra: han
Provides-Extra: lime
Requires-Dist: azureml-interpret (~=1.23.0)
Provides-Extra: han
Requires-Dist: spacy; extra == 'han'
Requires-Dist: gensim; extra == 'han'
Requires-Dist: tensorflow; extra == 'han'
Provides-Extra: lime
Requires-Dist: lime; extra == 'lime'
